{
  "Mexico": {
    "elo": 1881.3,
    "world_rank": null,
    "source": "fallback",
    "rd": 164.48186707797169,
    "volatility": 0.06
  },
  "South Korea": {
    "elo": 1765.1,
    "world_rank": null,
    "source": "fallback",
    "rd": 164.45015657147542,
    "volatility": 0.06
  },
  "South Africa": {
    "elo": 1599.3,
    "world_rank": null,
    "source": "fallback",
    "rd": 159.6838718489269,
    "volatility": 0.06
  },
  "Czechia": {
    "elo": 1750.5,
    "world_rank": null,
    "source": "fallback",
    "rd": 159.51744046059875,
    "volatility": 0.06
  },
  "Canada": {
    "elo": 1697.6,
    "world_rank": null,
    "source": "fallback",
    "rd": 155.44470391130739,
    "volatility": 0.06
  },
  "Switzerland": {
    "elo": 1874.9,
    "world_rank": null,
    "source": "fallback",
    "rd": 161.31776197375632,
    "volatility": 0.06
  },
  "Qatar": {
    "elo": 1555.2,
    "world_rank": null,
    "source": "fallback",
    "rd": 159.2307274907169,
    "volatility": 0.06
  },
  "Bosnia-Herzegovina": {
    "elo": 1689.9,
    "world_rank": null,
    "source": "fallback",
    "rd": 154.91556251406362,
    "volatility": 0.06
  },
  "Brazil": {
    "elo": 2066.0,
    "world_rank": null,
    "source": "fallback",
    "rd": 175.90275348479452,
    "volatility": 0.06
  },
  "Morocco": {
    "elo": 1891.7,
    "world_rank": null,
    "source": "fallback",
    "rd": 156.9319782323559,
    "volatility": 0.06
  },
  "Haiti": {
    "elo": 1436.9,
    "world_rank": null,
    "source": "fallback",
    "rd": 170.11098722539973,
    "volatility": 0.06
  },
  "Scotland": {
    "elo": 1738.9,
    "world_rank": null,
    "source": "fallback",
    "rd": 163.11997331874142,
    "volatility": 0.06
  },
  "USA": {
    "elo": 1853.4,
    "world_rank": null,
    "source": "fallback",
    "rd": 164.82554465489594,
    "volatility": 0.06
  },
  "Paraguay": {
    "elo": 1712.6,
    "world_rank": null,
    "source": "fallback",
    "rd": 157.14667984301965,
    "volatility": 0.06
  },
  "Australia": {
    "elo": 1770.9,
    "world_rank": null,
    "source": "fallback",
    "rd": 153.60911553908105,
    "volatility": 0.06
  },
  "T\u00fcrkiye": {
    "elo": 1760.8,
    "world_rank": null,
    "source": "fallback",
    "rd": 158.08060703301518,
    "volatility": 0.06
  },
  "Germany": {
    "elo": 1991.8,
    "world_rank": null,
    "source": "fallback",
    "rd": 179.05562087198635,
    "volatility": 0.06
  },
  "Cura\u00e7ao": {
    "elo": 1405.1,
    "world_rank": null,
    "source": "fallback",
    "rd": 184.8080858939032,
    "volatility": 0.06
  },
  "Ivory Coast": {
    "elo": 1738.8,
    "world_rank": null,
    "source": "fallback",
    "rd": 163.1865429921567,
    "volatility": 0.06
  },
  "Ecuador": {
    "elo": 1662.2,
    "world_rank": null,
    "source": "fallback",
    "rd": 160.71125843810827,
    "volatility": 0.06
  },
  "Netherlands": {
    "elo": 1973.0,
    "world_rank": null,
    "source": "fallback",
    "rd": 163.2248659262201,
    "volatility": 0.06
  },
  "Japan": {
    "elo": 1899.3,
    "world_rank": null,
    "source": "fallback",
    "rd": 168.6707859316608,
    "volatility": 0.06
  },
  "Sweden": {
    "elo": 1794.9,
    "world_rank": null,
    "source": "fallback",
    "rd": 160.44792064283016,
    "volatility": 0.06
  },
  "Tunisia": {
    "elo": 1664.8,
    "world_rank": null,
    "source": "fallback",
    "rd": 160.7396354500612,
    "volatility": 0.06
  },
  "Belgium": {
    "elo": 1912.1,
    "world_rank": null,
    "source": "fallback",
    "rd": 163.32369387463984,
    "volatility": 0.06
  },
  "Egypt": {
    "elo": 1708.5,
    "world_rank": null,
    "source": "fallback",
    "rd": 179.07664603223347,
    "volatility": 0.06
  },
  "Iran": {
    "elo": 1741.5,
    "world_rank": null,
    "source": "fallback",
    "rd": 163.38431399097334,
    "volatility": 0.06
  },
  "New Zealand": {
    "elo": 1519.1,
    "world_rank": null,
    "source": "fallback",
    "rd": 181.8278260911439,
    "volatility": 0.06
  },
  "Spain": {
    "elo": 2028.6,
    "world_rank": null,
    "source": "fallback",
    "rd": 178.1848873401153,
    "volatility": 0.06
  },
  "Cabo Verde": {
    "elo": 1628.6,
    "world_rank": null,
    "source": "fallback",
    "rd": 193.37186966095786,
    "volatility": 0.06
  },
  "Saudi Arabia": {
    "elo": 1631.8,
    "world_rank": null,
    "source": "fallback",
    "rd": 156.42933862691845,
    "volatility": 0.06
  },
  "Uruguay": {
    "elo": 1885.1,
    "world_rank": null,
    "source": "fallback",
    "rd": 186.85292345831826,
    "volatility": 0.06
  },
  "France": {
    "elo": 2044.8,
    "world_rank": null,
    "source": "fallback",
    "rd": 177.06985648563094,
    "volatility": 0.06
  },
  "Senegal": {
    "elo": 1747.2,
    "world_rank": null,
    "source": "fallback",
    "rd": 172.36313007281797,
    "volatility": 0.06
  },
  "Norway": {
    "elo": 1824.5,
    "world_rank": null,
    "source": "fallback",
    "rd": 168.82710447765083,
    "volatility": 0.06
  },
  "Iraq": {
    "elo": 1587.8,
    "world_rank": null,
    "source": "fallback",
    "rd": 166.22018251287616,
    "volatility": 0.06
  },
  "Argentina": {
    "elo": 2146.3,
    "world_rank": null,
    "source": "fallback",
    "rd": 187.36112038122428,
    "volatility": 0.06
  },
  "Algeria": {
    "elo": 1771.8,
    "world_rank": null,
    "source": "fallback",
    "rd": 180.5373167594746,
    "volatility": 0.06
  },
  "Austria": {
    "elo": 1833.3,
    "world_rank": null,
    "source": "fallback",
    "rd": 188.99425521191043,
    "volatility": 0.06
  },
  "Jordan": {
    "elo": 1512.3,
    "world_rank": null,
    "source": "fallback",
    "rd": 180.68794933002152,
    "volatility": 0.06
  },
  "Portugal": {
    "elo": 1981.2,
    "world_rank": null,
    "source": "fallback",
    "rd": 185.6450943695531,
    "volatility": 0.06
  },
  "Colombia": {
    "elo": 1855.0,
    "world_rank": null,
    "source": "fallback",
    "rd": 180.87139206813774,
    "volatility": 0.06
  },
  "Congo DR": {
    "elo": 1561.7,
    "world_rank": null,
    "source": "fallback",
    "rd": 175.9584150758804,
    "volatility": 0.06
  },
  "Uzbekistan": {
    "elo": 1525.0,
    "world_rank": null,
    "source": "fallback",
    "rd": 183.9559272934939,
    "volatility": 0.06
  },
  "England": {
    "elo": 2016.4,
    "world_rank": null,
    "source": "fallback",
    "rd": 174.1171169002776,
    "volatility": 0.06
  },
  "Croatia": {
    "elo": 1887.9,
    "world_rank": null,
    "source": "fallback",
    "rd": 175.32497420879724,
    "volatility": 0.06
  },
  "Ghana": {
    "elo": 1657.5,
    "world_rank": null,
    "source": "fallback",
    "rd": 179.20062797731111,
    "volatility": 0.06
  },
  "Panama": {
    "elo": 1582.9,
    "world_rank": null,
    "source": "fallback",
    "rd": 166.2047350624771,
    "volatility": 0.06
  }
}