{
  "simulations": 10000,
  "predicted_winner": "Spain",
  "predicted_winner_probability_pct": 9.35,
  "all_teams": [
    {
      "team": "Spain",
      "count": 935,
      "probability": 9.35,
      "ci_low": 8.9834,
      "ci_high": 9.7299
    },
    {
      "team": "Netherlands",
      "count": 697,
      "probability": 6.97,
      "ci_low": 6.6506,
      "ci_high": 7.3036
    },
    {
      "team": "Argentina",
      "count": 691,
      "probability": 6.91,
      "ci_low": 6.5919,
      "ci_high": 7.2423
    },
    {
      "team": "Germany",
      "count": 584,
      "probability": 5.84,
      "ci_low": 5.5466,
      "ci_high": 6.1479
    },
    {
      "team": "France",
      "count": 536,
      "probability": 5.36,
      "ci_low": 5.0785,
      "ci_high": 5.6561
    },
    {
      "team": "Brazil",
      "count": 464,
      "probability": 4.64,
      "ci_low": 4.3777,
      "ci_high": 4.9172
    },
    {
      "team": "Mexico",
      "count": 460,
      "probability": 4.6,
      "ci_low": 4.3388,
      "ci_high": 4.8761
    },
    {
      "team": "England",
      "count": 393,
      "probability": 3.93,
      "ci_low": 3.6884,
      "ci_high": 4.1868
    },
    {
      "team": "Portugal",
      "count": 376,
      "probability": 3.76,
      "ci_low": 3.5236,
      "ci_high": 4.0116
    },
    {
      "team": "USA",
      "count": 360,
      "probability": 3.6,
      "ci_low": 3.3687,
      "ci_high": 3.8466
    },
    {
      "team": "Croatia",
      "count": 342,
      "probability": 3.42,
      "ci_low": 3.1946,
      "ci_high": 3.6608
    },
    {
      "team": "Morocco",
      "count": 339,
      "probability": 3.39,
      "ci_low": 3.1655,
      "ci_high": 3.6298
    },
    {
      "team": "Colombia",
      "count": 306,
      "probability": 3.06,
      "ci_low": 2.8468,
      "ci_high": 3.2886
    },
    {
      "team": "Uruguay",
      "count": 267,
      "probability": 2.67,
      "ci_low": 2.471,
      "ci_high": 2.8846
    },
    {
      "team": "Senegal",
      "count": 247,
      "probability": 2.47,
      "ci_low": 2.2787,
      "ci_high": 2.6769
    },
    {
      "team": "Belgium",
      "count": 236,
      "probability": 2.36,
      "ci_low": 2.1731,
      "ci_high": 2.5626
    },
    {
      "team": "Norway",
      "count": 224,
      "probability": 2.24,
      "ci_low": 2.058,
      "ci_high": 2.4377
    },
    {
      "team": "Austria",
      "count": 210,
      "probability": 2.1,
      "ci_low": 1.9239,
      "ci_high": 2.2918
    },
    {
      "team": "Sweden",
      "count": 204,
      "probability": 2.04,
      "ci_low": 1.8665,
      "ci_high": 2.2293
    },
    {
      "team": "T\u00fcrkiye",
      "count": 162,
      "probability": 1.62,
      "ci_low": 1.4659,
      "ci_high": 1.79
    },
    {
      "team": "Scotland",
      "count": 149,
      "probability": 1.49,
      "ci_low": 1.3425,
      "ci_high": 1.6535
    },
    {
      "team": "Switzerland",
      "count": 145,
      "probability": 1.45,
      "ci_low": 1.3045,
      "ci_high": 1.6114
    },
    {
      "team": "Japan",
      "count": 129,
      "probability": 1.29,
      "ci_low": 1.1531,
      "ci_high": 1.4429
    },
    {
      "team": "South Korea",
      "count": 128,
      "probability": 1.28,
      "ci_low": 1.1437,
      "ci_high": 1.4323
    },
    {
      "team": "Australia",
      "count": 118,
      "probability": 1.18,
      "ci_low": 1.0494,
      "ci_high": 1.3267
    },
    {
      "team": "Canada",
      "count": 118,
      "probability": 1.18,
      "ci_low": 1.0494,
      "ci_high": 1.3267
    },
    {
      "team": "Czechia",
      "count": 115,
      "probability": 1.15,
      "ci_low": 1.0211,
      "ci_high": 1.2949
    },
    {
      "team": "Tunisia",
      "count": 108,
      "probability": 1.08,
      "ci_low": 0.9553,
      "ci_high": 1.2208
    },
    {
      "team": "Iran",
      "count": 99,
      "probability": 0.99,
      "ci_low": 0.8709,
      "ci_high": 1.1252
    },
    {
      "team": "Algeria",
      "count": 94,
      "probability": 0.94,
      "ci_low": 0.8241,
      "ci_high": 1.072
    },
    {
      "team": "Ecuador",
      "count": 75,
      "probability": 0.75,
      "ci_low": 0.6472,
      "ci_high": 0.869
    },
    {
      "team": "Paraguay",
      "count": 65,
      "probability": 0.65,
      "ci_low": 0.5548,
      "ci_high": 0.7614
    },
    {
      "team": "Ivory Coast",
      "count": 65,
      "probability": 0.65,
      "ci_low": 0.5548,
      "ci_high": 0.7614
    },
    {
      "team": "Ghana",
      "count": 60,
      "probability": 0.6,
      "ci_low": 0.5088,
      "ci_high": 0.7074
    },
    {
      "team": "Egypt",
      "count": 59,
      "probability": 0.59,
      "ci_low": 0.4996,
      "ci_high": 0.6966
    },
    {
      "team": "Saudi Arabia",
      "count": 58,
      "probability": 0.58,
      "ci_low": 0.4904,
      "ci_high": 0.6858
    },
    {
      "team": "Panama",
      "count": 52,
      "probability": 0.52,
      "ci_low": 0.4356,
      "ci_high": 0.6207
    },
    {
      "team": "South Africa",
      "count": 45,
      "probability": 0.45,
      "ci_low": 0.372,
      "ci_high": 0.5443
    },
    {
      "team": "Iraq",
      "count": 44,
      "probability": 0.44,
      "ci_low": 0.3629,
      "ci_high": 0.5334
    },
    {
      "team": "Bosnia-Herzegovina",
      "count": 37,
      "probability": 0.37,
      "ci_low": 0.2999,
      "ci_high": 0.4564
    },
    {
      "team": "Cabo Verde",
      "count": 33,
      "probability": 0.33,
      "ci_low": 0.2642,
      "ci_high": 0.4121
    },
    {
      "team": "Uzbekistan",
      "count": 28,
      "probability": 0.28,
      "ci_low": 0.2199,
      "ci_high": 0.3564
    },
    {
      "team": "Congo DR",
      "count": 27,
      "probability": 0.27,
      "ci_low": 0.2112,
      "ci_high": 0.3452
    },
    {
      "team": "Qatar",
      "count": 27,
      "probability": 0.27,
      "ci_low": 0.2112,
      "ci_high": 0.3452
    },
    {
      "team": "Haiti",
      "count": 27,
      "probability": 0.27,
      "ci_low": 0.2112,
      "ci_high": 0.3452
    },
    {
      "team": "Jordan",
      "count": 26,
      "probability": 0.26,
      "ci_low": 0.2024,
      "ci_high": 0.334
    },
    {
      "team": "New Zealand",
      "count": 25,
      "probability": 0.25,
      "ci_low": 0.1936,
      "ci_high": 0.3227
    },
    {
      "team": "Cura\u00e7ao",
      "count": 11,
      "probability": 0.11,
      "ci_low": 0.0749,
      "ci_high": 0.1615
    }
  ],
  "runners_up": [
    {
      "team": "Argentina",
      "count": 701,
      "probability": 7.01
    },
    {
      "team": "Netherlands",
      "count": 509,
      "probability": 5.09
    },
    {
      "team": "France",
      "count": 454,
      "probability": 4.54
    },
    {
      "team": "Brazil",
      "count": 450,
      "probability": 4.5
    },
    {
      "team": "Germany",
      "count": 441,
      "probability": 4.41
    },
    {
      "team": "England",
      "count": 425,
      "probability": 4.25
    },
    {
      "team": "Portugal",
      "count": 419,
      "probability": 4.19
    },
    {
      "team": "Croatia",
      "count": 379,
      "probability": 3.79
    },
    {
      "team": "Mexico",
      "count": 370,
      "probability": 3.7
    }
  ],
  "third_place": [
    {
      "team": "Netherlands",
      "count": 540,
      "probability": 5.4
    },
    {
      "team": "Argentina",
      "count": 589,
      "probability": 5.89
    },
    {
      "team": "Germany",
      "count": 469,
      "probability": 4.69
    },
    {
      "team": "France",
      "count": 443,
      "probability": 4.43
    },
    {
      "team": "Brazil",
      "count": 430,
      "probability": 4.3
    },
    {
      "team": "Portugal",
      "count": 388,
      "probability": 3.88
    },
    {
      "team": "Croatia",
      "count": 383,
      "probability": 3.83
    },
    {
      "team": "Mexico",
      "count": 381,
      "probability": 3.81
    },
    {
      "team": "England",
      "count": 375,
      "probability": 3.75
    }
  ],
  "match_probabilities": [
    {
      "home": "Mexico",
      "away": "South Africa",
      "lambda_home": 2.0297,
      "lambda_away": 1.1085,
      "skellam_win": 0.586473,
      "skellam_draw": 0.211624,
      "skellam_loss": 0.201903
    },
    {
      "home": "South Korea",
      "away": "Czechia",
      "lambda_home": 1.5506,
      "lambda_away": 1.4511,
      "skellam_win": 0.400562,
      "skellam_draw": 0.2426,
      "skellam_loss": 0.356838
    },
    {
      "home": "Canada",
      "away": "Bosnia-Herzegovina",
      "lambda_home": 1.5808,
      "lambda_away": 1.4234,
      "skellam_win": 0.413557,
      "skellam_draw": 0.242,
      "skellam_loss": 0.344443
    },
    {
      "home": "USA",
      "away": "Paraguay",
      "lambda_home": 1.8138,
      "lambda_away": 1.2405,
      "skellam_win": 0.508432,
      "skellam_draw": 0.230157,
      "skellam_loss": 0.261411
    },
    {
      "home": "Qatar",
      "away": "Switzerland",
      "lambda_home": 1.0459,
      "lambda_away": 2.1513,
      "skellam_win": 0.174481,
      "skellam_draw": 0.199516,
      "skellam_loss": 0.626003
    },
    {
      "home": "Brazil",
      "away": "Morocco",
      "lambda_home": 1.9782,
      "lambda_away": 1.1374,
      "skellam_win": 0.568757,
      "skellam_draw": 0.216472,
      "skellam_loss": 0.214771
    },
    {
      "home": "Haiti",
      "away": "Scotland",
      "lambda_home": 1.0806,
      "lambda_away": 2.0822,
      "skellam_win": 0.189581,
      "skellam_draw": 0.206496,
      "skellam_loss": 0.603923
    },
    {
      "home": "Australia",
      "away": "T\u00fcrkiye",
      "lambda_home": 1.5312,
      "lambda_away": 1.4694,
      "skellam_win": 0.392162,
      "skellam_draw": 0.242846,
      "skellam_loss": 0.364992
    },
    {
      "home": "Germany",
      "away": "Cura\u00e7ao",
      "lambda_home": 3.5,
      "lambda_away": 0.492,
      "skellam_win": 0.90919,
      "skellam_draw": 0.066861,
      "skellam_loss": 0.023949
    },
    {
      "home": "Netherlands",
      "away": "Japan",
      "lambda_home": 2.3442,
      "lambda_away": 0.9598,
      "skellam_win": 0.682331,
      "skellam_draw": 0.179301,
      "skellam_loss": 0.138369
    },
    {
      "home": "Ivory Coast",
      "away": "Ecuador",
      "lambda_home": 1.5508,
      "lambda_away": 1.4509,
      "skellam_win": 0.40066,
      "skellam_draw": 0.242597,
      "skellam_loss": 0.356744
    },
    {
      "home": "Sweden",
      "away": "Tunisia",
      "lambda_home": 1.6332,
      "lambda_away": 1.3777,
      "skellam_win": 0.435758,
      "skellam_draw": 0.240376,
      "skellam_loss": 0.323866
    },
    {
      "home": "Spain",
      "away": "Cabo Verde",
      "lambda_home": 3.1502,
      "lambda_away": 0.7143,
      "skellam_win": 0.844883,
      "skellam_draw": 0.102376,
      "skellam_loss": 0.052741
    },
    {
      "home": "Belgium",
      "away": "Egypt",
      "lambda_home": 2.1608,
      "lambda_away": 1.0413,
      "skellam_win": 0.628968,
      "skellam_draw": 0.198538,
      "skellam_loss": 0.172494
    },
    {
      "home": "Saudi Arabia",
      "away": "Uruguay",
      "lambda_home": 1.1669,
      "lambda_away": 1.9282,
      "skellam_win": 0.228022,
      "skellam_draw": 0.220956,
      "skellam_loss": 0.551022
    },
    {
      "home": "Iran",
      "away": "New Zealand",
      "lambda_home": 2.159,
      "lambda_away": 1.0422,
      "skellam_win": 0.628393,
      "skellam_draw": 0.198728,
      "skellam_loss": 0.172879
    },
    {
      "home": "France",
      "away": "Senegal",
      "lambda_home": 2.2611,
      "lambda_away": 0.9951,
      "skellam_win": 0.659007,
      "skellam_draw": 0.188084,
      "skellam_loss": 0.152908
    },
    {
      "home": "Iraq",
      "away": "Norway",
      "lambda_home": 1.1591,
      "lambda_away": 1.9411,
      "skellam_win": 0.224527,
      "skellam_draw": 0.219822,
      "skellam_loss": 0.555652
    },
    {
      "home": "Argentina",
      "away": "Algeria",
      "lambda_home": 2.5181,
      "lambda_away": 0.8935,
      "skellam_win": 0.726721,
      "skellam_draw": 0.161005,
      "skellam_loss": 0.112273
    },
    {
      "home": "Austria",
      "away": "Jordan",
      "lambda_home": 2.1797,
      "lambda_away": 1.0322,
      "skellam_win": 0.634802,
      "skellam_draw": 0.196584,
      "skellam_loss": 0.168614
    },
    {
      "home": "Portugal",
      "away": "Congo DR",
      "lambda_home": 2.8133,
      "lambda_away": 0.7998,
      "skellam_win": 0.789553,
      "skellam_draw": 0.131631,
      "skellam_loss": 0.078816
    },
    {
      "home": "England",
      "away": "Croatia",
      "lambda_home": 1.5596,
      "lambda_away": 1.4427,
      "skellam_win": 0.404475,
      "skellam_draw": 0.242447,
      "skellam_loss": 0.353078
    },
    {
      "home": "Ghana",
      "away": "Panama",
      "lambda_home": 1.5233,
      "lambda_away": 1.477,
      "skellam_win": 0.388716,
      "skellam_draw": 0.242914,
      "skellam_loss": 0.368371
    },
    {
      "home": "Uzbekistan",
      "away": "Colombia",
      "lambda_home": 0.7901,
      "lambda_away": 2.8477,
      "skellam_win": 0.075634,
      "skellam_draw": 0.128409,
      "skellam_loss": 0.795957
    },
    {
      "home": "Czechia",
      "away": "South Africa",
      "lambda_home": 1.7712,
      "lambda_away": 1.2703,
      "skellam_win": 0.491848,
      "skellam_draw": 0.233118,
      "skellam_loss": 0.275034
    },
    {
      "home": "Switzerland",
      "away": "Bosnia-Herzegovina",
      "lambda_home": 1.9062,
      "lambda_away": 1.1803,
      "skellam_win": 0.543053,
      "skellam_draw": 0.222848,
      "skellam_loss": 0.234099
    },
    {
      "home": "Canada",
      "away": "Qatar",
      "lambda_home": 1.784,
      "lambda_away": 1.2612,
      "skellam_win": 0.496856,
      "skellam_draw": 0.232262,
      "skellam_loss": 0.270882
    },
    {
      "home": "Mexico",
      "away": "South Korea",
      "lambda_home": 1.6629,
      "lambda_away": 1.353,
      "skellam_win": 0.448156,
      "skellam_draw": 0.239152,
      "skellam_loss": 0.312692
    },
    {
      "home": "USA",
      "away": "Australia",
      "lambda_home": 1.602,
      "lambda_away": 1.4045,
      "skellam_win": 0.422629,
      "skellam_draw": 0.241426,
      "skellam_loss": 0.335945
    },
    {
      "home": "Scotland",
      "away": "Morocco",
      "lambda_home": 1.27,
      "lambda_away": 1.7716,
      "skellam_win": 0.274879,
      "skellam_draw": 0.233087,
      "skellam_loss": 0.492034
    },
    {
      "home": "Brazil",
      "away": "Haiti",
      "lambda_home": 3.2433,
      "lambda_away": 0.6937,
      "skellam_win": 0.857576,
      "skellam_draw": 0.095206,
      "skellam_loss": 0.047218
    },
    {
      "home": "T\u00fcrkiye",
      "away": "Paraguay",
      "lambda_home": 1.6637,
      "lambda_away": 1.3524,
      "skellam_win": 0.448473,
      "skellam_draw": 0.239118,
      "skellam_loss": 0.312409
    },
    {
      "home": "Netherlands",
      "away": "Sweden",
      "lambda_home": 2.2933,
      "lambda_away": 0.9811,
      "skellam_win": 0.66823,
      "skellam_draw": 0.18468,
      "skellam_loss": 0.14709
    },
    {
      "home": "Germany",
      "away": "Ivory Coast",
      "lambda_home": 2.4994,
      "lambda_away": 0.9002,
      "skellam_win": 0.722231,
      "skellam_draw": 0.162949,
      "skellam_loss": 0.11482
    },
    {
      "home": "Ecuador",
      "away": "Cura\u00e7ao",
      "lambda_home": 2.6549,
      "lambda_away": 0.8475,
      "skellam_win": 0.757682,
      "skellam_draw": 0.147038,
      "skellam_loss": 0.09528
    },
    {
      "home": "Tunisia",
      "away": "Japan",
      "lambda_home": 1.4082,
      "lambda_away": 1.5977,
      "skellam_win": 0.337646,
      "skellam_draw": 0.241552,
      "skellam_loss": 0.420802
    },
    {
      "home": "Spain",
      "away": "Saudi Arabia",
      "lambda_home": 3.0478,
      "lambda_away": 0.7382,
      "skellam_win": 0.829699,
      "skellam_draw": 0.110726,
      "skellam_loss": 0.059575
    },
    {
      "home": "Belgium",
      "away": "Iran",
      "lambda_home": 2.0257,
      "lambda_away": 1.1107,
      "skellam_win": 0.585125,
      "skellam_draw": 0.212006,
      "skellam_loss": 0.202869
    },
    {
      "home": "Uruguay",
      "away": "Cabo Verde",
      "lambda_home": 1.993,
      "lambda_away": 1.1289,
      "skellam_win": 0.573905,
      "skellam_draw": 0.215101,
      "skellam_loss": 0.210994
    },
    {
      "home": "New Zealand",
      "away": "Egypt",
      "lambda_home": 1.1117,
      "lambda_away": 2.024,
      "skellam_win": 0.203293,
      "skellam_draw": 0.212172,
      "skellam_loss": 0.584535
    },
    {
      "home": "Argentina",
      "away": "Austria",
      "lambda_home": 2.3898,
      "lambda_away": 0.9415,
      "skellam_win": 0.694557,
      "skellam_draw": 0.174467,
      "skellam_loss": 0.130977
    },
    {
      "home": "France",
      "away": "Iraq",
      "lambda_home": 2.8735,
      "lambda_away": 0.783,
      "skellam_win": 0.800629,
      "skellam_draw": 0.126031,
      "skellam_loss": 0.07334
    },
    {
      "home": "Norway",
      "away": "Senegal",
      "lambda_home": 1.5274,
      "lambda_away": 1.4731,
      "skellam_win": 0.3905,
      "skellam_draw": 0.242881,
      "skellam_loss": 0.366619
    },
    {
      "home": "Jordan",
      "away": "Algeria",
      "lambda_home": 1.0876,
      "lambda_away": 2.0687,
      "skellam_win": 0.192671,
      "skellam_draw": 0.207828,
      "skellam_loss": 0.599501
    },
    {
      "home": "Portugal",
      "away": "Uzbekistan",
      "lambda_home": 3.011,
      "lambda_away": 0.7473,
      "skellam_win": 0.823918,
      "skellam_draw": 0.11384,
      "skellam_loss": 0.062241
    },
    {
      "home": "England",
      "away": "Ghana",
      "lambda_home": 2.5739,
      "lambda_away": 0.8742,
      "skellam_win": 0.739753,
      "skellam_draw": 0.155247,
      "skellam_loss": 0.105
    },
    {
      "home": "Panama",
      "away": "Croatia",
      "lambda_home": 0.895,
      "lambda_away": 2.514,
      "skellam_win": 0.112832,
      "skellam_draw": 0.161435,
      "skellam_loss": 0.725733
    },
    {
      "home": "Colombia",
      "away": "Congo DR",
      "lambda_home": 2.6607,
      "lambda_away": 0.8456,
      "skellam_win": 0.758937,
      "skellam_draw": 0.146451,
      "skellam_loss": 0.094612
    },
    {
      "home": "Switzerland",
      "away": "Canada",
      "lambda_home": 1.8089,
      "lambda_away": 1.2439,
      "skellam_win": 0.506516,
      "skellam_draw": 0.230517,
      "skellam_loss": 0.262966
    },
    {
      "home": "Bosnia-Herzegovina",
      "away": "Qatar",
      "lambda_home": 1.6928,
      "lambda_away": 1.3291,
      "skellam_win": 0.460447,
      "skellam_draw": 0.237722,
      "skellam_loss": 0.301832
    },
    {
      "home": "Scotland",
      "away": "Brazil",
      "lambda_home": 0.963,
      "lambda_away": 2.3365,
      "skellam_win": 0.139659,
      "skellam_draw": 0.180118,
      "skellam_loss": 0.680223
    },
    {
      "home": "Morocco",
      "away": "Haiti",
      "lambda_home": 2.4593,
      "lambda_away": 0.9149,
      "skellam_win": 0.712355,
      "skellam_draw": 0.16715,
      "skellam_loss": 0.120494
    },
    {
      "home": "Czechia",
      "away": "Mexico",
      "lambda_home": 1.3089,
      "lambda_away": 1.719,
      "skellam_win": 0.292621,
      "skellam_draw": 0.236316,
      "skellam_loss": 0.471063
    },
    {
      "home": "South Africa",
      "away": "South Korea",
      "lambda_home": 1.2289,
      "lambda_away": 1.8309,
      "skellam_win": 0.256155,
      "skellam_draw": 0.228896,
      "skellam_loss": 0.514949
    },
    {
      "home": "Cura\u00e7ao",
      "away": "Ivory Coast",
      "lambda_home": 0.8197,
      "lambda_away": 2.7448,
      "skellam_win": 0.085551,
      "skellam_draw": 0.13818,
      "skellam_loss": 0.776269
    },
    {
      "home": "Ecuador",
      "away": "Germany",
      "lambda_home": 0.8707,
      "lambda_away": 2.584,
      "skellam_win": 0.103728,
      "skellam_draw": 0.154207,
      "skellam_loss": 0.742065
    },
    {
      "home": "Japan",
      "away": "Sweden",
      "lambda_home": 1.4675,
      "lambda_away": 1.5333,
      "skellam_win": 0.364125,
      "skellam_draw": 0.242825,
      "skellam_loss": 0.39305
    },
    {
      "home": "Tunisia",
      "away": "Netherlands",
      "lambda_home": 0.9011,
      "lambda_away": 2.4969,
      "skellam_win": 0.115165,
      "skellam_draw": 0.16321,
      "skellam_loss": 0.721625
    },
    {
      "home": "T\u00fcrkiye",
      "away": "USA",
      "lambda_home": 1.3758,
      "lambda_away": 1.6354,
      "skellam_win": 0.323021,
      "skellam_draw": 0.240292,
      "skellam_loss": 0.436687
    },
    {
      "home": "Paraguay",
      "away": "Australia",
      "lambda_home": 1.3248,
      "lambda_away": 1.6983,
      "skellam_win": 0.299876,
      "skellam_draw": 0.237438,
      "skellam_loss": 0.462686
    },
    {
      "home": "Norway",
      "away": "France",
      "lambda_home": 1.0133,
      "lambda_away": 2.2205,
      "skellam_win": 0.16055,
      "skellam_draw": 0.192342,
      "skellam_loss": 0.647109
    },
    {
      "home": "Senegal",
      "away": "Iraq",
      "lambda_home": 1.9063,
      "lambda_away": 1.1803,
      "skellam_win": 0.543076,
      "skellam_draw": 0.222842,
      "skellam_loss": 0.234081
    },
    {
      "home": "Cabo Verde",
      "away": "Saudi Arabia",
      "lambda_home": 1.4512,
      "lambda_away": 1.5504,
      "skellam_win": 0.356907,
      "skellam_draw": 0.242603,
      "skellam_loss": 0.400491
    },
    {
      "home": "Uruguay",
      "away": "Spain",
      "lambda_home": 0.949,
      "lambda_away": 2.3709,
      "skellam_win": 0.133992,
      "skellam_draw": 0.17647,
      "skellam_loss": 0.689537
    },
    {
      "home": "Egypt",
      "away": "Iran",
      "lambda_home": 1.4062,
      "lambda_away": 1.6,
      "skellam_win": 0.336748,
      "skellam_draw": 0.241486,
      "skellam_loss": 0.421766
    },
    {
      "home": "New Zealand",
      "away": "Belgium",
      "lambda_home": 0.7717,
      "lambda_away": 2.9157,
      "skellam_win": 0.06974,
      "skellam_draw": 0.122206,
      "skellam_loss": 0.808054
    },
    {
      "home": "Panama",
      "away": "England",
      "lambda_home": 0.8608,
      "lambda_away": 2.6139,
      "skellam_win": 0.100081,
      "skellam_draw": 0.151168,
      "skellam_loss": 0.748751
    },
    {
      "home": "Croatia",
      "away": "Ghana",
      "lambda_home": 2.4755,
      "lambda_away": 0.9089,
      "skellam_win": 0.716384,
      "skellam_draw": 0.165449,
      "skellam_loss": 0.118167
    },
    {
      "home": "Colombia",
      "away": "Portugal",
      "lambda_home": 1.4187,
      "lambda_away": 1.586,
      "skellam_win": 0.342333,
      "skellam_draw": 0.24187,
      "skellam_loss": 0.415797
    },
    {
      "home": "Congo DR",
      "away": "Uzbekistan",
      "lambda_home": 1.6054,
      "lambda_away": 1.4015,
      "skellam_win": 0.424066,
      "skellam_draw": 0.241324,
      "skellam_loss": 0.33461
    },
    {
      "home": "Algeria",
      "away": "Austria",
      "lambda_home": 1.4236,
      "lambda_away": 1.5805,
      "skellam_win": 0.344549,
      "skellam_draw": 0.242006,
      "skellam_loss": 0.413445
    },
    {
      "home": "Jordan",
      "away": "Argentina",
      "lambda_home": 0.6479,
      "lambda_away": 3.4728,
      "skellam_win": 0.035982,
      "skellam_draw": 0.07923,
      "skellam_loss": 0.884788
    },
    {
      "home": "2ND GROUP A",
      "away": "2ND GROUP B",
      "lambda_home": 1.5,
      "lambda_away": 1.5,
      "skellam_win": 0.3785,
      "skellam_draw": 0.243,
      "skellam_loss": 0.3785
    },
    {
      "home": "1ST GROUP E",
      "away": "3RD PLACE (POOL)",
      "lambda_home": 1.5,
      "lambda_away": 1.5,
      "skellam_win": 0.3785,
      "skellam_draw": 0.243,
      "skellam_loss": 0.3785
    },
    {
      "home": "1ST GROUP F",
      "away": "2ND GROUP C",
      "lambda_home": 1.5,
      "lambda_away": 1.5,
      "skellam_win": 0.3785,
      "skellam_draw": 0.243,
      "skellam_loss": 0.3785
    },
    {
      "home": "1ST GROUP C",
      "away": "2ND GROUP F",
      "lambda_home": 1.5,
      "lambda_away": 1.5,
      "skellam_win": 0.3785,
      "skellam_draw": 0.243,
      "skellam_loss": 0.3785
    },
    {
      "home": "1ST GROUP I",
      "away": "3RD PLACE (POOL)",
      "lambda_home": 1.5,
      "lambda_away": 1.5,
      "skellam_win": 0.3785,
      "skellam_draw": 0.243,
      "skellam_loss": 0.3785
    },
    {
      "home": "2ND GROUP E",
      "away": "2ND GROUP I",
      "lambda_home": 1.5,
      "lambda_away": 1.5,
      "skellam_win": 0.3785,
      "skellam_draw": 0.243,
      "skellam_loss": 0.3785
    },
    {
      "home": "1ST GROUP A",
      "away": "3RD PLACE (POOL)",
      "lambda_home": 1.5,
      "lambda_away": 1.5,
      "skellam_win": 0.3785,
      "skellam_draw": 0.243,
      "skellam_loss": 0.3785
    },
    {
      "home": "1ST GROUP L",
      "away": "3RD PLACE (POOL)",
      "lambda_home": 1.5,
      "lambda_away": 1.5,
      "skellam_win": 0.3785,
      "skellam_draw": 0.243,
      "skellam_loss": 0.3785
    },
    {
      "home": "1ST GROUP D",
      "away": "3RD PLACE (POOL)",
      "lambda_home": 1.5,
      "lambda_away": 1.5,
      "skellam_win": 0.3785,
      "skellam_draw": 0.243,
      "skellam_loss": 0.3785
    },
    {
      "home": "1ST GROUP G",
      "away": "3RD PLACE (POOL)",
      "lambda_home": 1.5,
      "lambda_away": 1.5,
      "skellam_win": 0.3785,
      "skellam_draw": 0.243,
      "skellam_loss": 0.3785
    },
    {
      "home": "2ND GROUP K",
      "away": "2ND GROUP L",
      "lambda_home": 1.5,
      "lambda_away": 1.5,
      "skellam_win": 0.3785,
      "skellam_draw": 0.243,
      "skellam_loss": 0.3785
    },
    {
      "home": "1ST GROUP H",
      "away": "2ND GROUP J",
      "lambda_home": 1.5,
      "lambda_away": 1.5,
      "skellam_win": 0.3785,
      "skellam_draw": 0.243,
      "skellam_loss": 0.3785
    },
    {
      "home": "1ST GROUP B",
      "away": "3RD PLACE (POOL)",
      "lambda_home": 1.5,
      "lambda_away": 1.5,
      "skellam_win": 0.3785,
      "skellam_draw": 0.243,
      "skellam_loss": 0.3785
    },
    {
      "home": "1ST GROUP J",
      "away": "2ND GROUP H",
      "lambda_home": 1.5,
      "lambda_away": 1.5,
      "skellam_win": 0.3785,
      "skellam_draw": 0.243,
      "skellam_loss": 0.3785
    },
    {
      "home": "1ST GROUP K",
      "away": "3RD PLACE (POOL)",
      "lambda_home": 1.5,
      "lambda_away": 1.5,
      "skellam_win": 0.3785,
      "skellam_draw": 0.243,
      "skellam_loss": 0.3785
    },
    {
      "home": "2ND GROUP D",
      "away": "2ND GROUP G",
      "lambda_home": 1.5,
      "lambda_away": 1.5,
      "skellam_win": 0.3785,
      "skellam_draw": 0.243,
      "skellam_loss": 0.3785
    },
    {
      "home": "WINNER M74",
      "away": "WINNER M77",
      "lambda_home": 1.5,
      "lambda_away": 1.5,
      "skellam_win": 0.3785,
      "skellam_draw": 0.243,
      "skellam_loss": 0.3785
    },
    {
      "home": "WINNER M73",
      "away": "WINNER M75",
      "lambda_home": 1.5,
      "lambda_away": 1.5,
      "skellam_win": 0.3785,
      "skellam_draw": 0.243,
      "skellam_loss": 0.3785
    },
    {
      "home": "WINNER M76",
      "away": "WINNER M78",
      "lambda_home": 1.5,
      "lambda_away": 1.5,
      "skellam_win": 0.3785,
      "skellam_draw": 0.243,
      "skellam_loss": 0.3785
    },
    {
      "home": "WINNER M79",
      "away": "WINNER M80",
      "lambda_home": 1.5,
      "lambda_away": 1.5,
      "skellam_win": 0.3785,
      "skellam_draw": 0.243,
      "skellam_loss": 0.3785
    },
    {
      "home": "WINNER M83",
      "away": "WINNER M84",
      "lambda_home": 1.5,
      "lambda_away": 1.5,
      "skellam_win": 0.3785,
      "skellam_draw": 0.243,
      "skellam_loss": 0.3785
    },
    {
      "home": "WINNER M81",
      "away": "WINNER M82",
      "lambda_home": 1.5,
      "lambda_away": 1.5,
      "skellam_win": 0.3785,
      "skellam_draw": 0.243,
      "skellam_loss": 0.3785
    },
    {
      "home": "WINNER M86",
      "away": "WINNER M88",
      "lambda_home": 1.5,
      "lambda_away": 1.5,
      "skellam_win": 0.3785,
      "skellam_draw": 0.243,
      "skellam_loss": 0.3785
    },
    {
      "home": "WINNER M85",
      "away": "WINNER M87",
      "lambda_home": 1.5,
      "lambda_away": 1.5,
      "skellam_win": 0.3785,
      "skellam_draw": 0.243,
      "skellam_loss": 0.3785
    },
    {
      "home": "WINNER M89",
      "away": "WINNER M90",
      "lambda_home": 1.5,
      "lambda_away": 1.5,
      "skellam_win": 0.3785,
      "skellam_draw": 0.243,
      "skellam_loss": 0.3785
    },
    {
      "home": "WINNER M93",
      "away": "WINNER M94",
      "lambda_home": 1.5,
      "lambda_away": 1.5,
      "skellam_win": 0.3785,
      "skellam_draw": 0.243,
      "skellam_loss": 0.3785
    },
    {
      "home": "WINNER M91",
      "away": "WINNER M92",
      "lambda_home": 1.5,
      "lambda_away": 1.5,
      "skellam_win": 0.3785,
      "skellam_draw": 0.243,
      "skellam_loss": 0.3785
    },
    {
      "home": "WINNER M95",
      "away": "WINNER M96",
      "lambda_home": 1.5,
      "lambda_away": 1.5,
      "skellam_win": 0.3785,
      "skellam_draw": 0.243,
      "skellam_loss": 0.3785
    },
    {
      "home": "WINNER M97",
      "away": "WINNER M98",
      "lambda_home": 1.5,
      "lambda_away": 1.5,
      "skellam_win": 0.3785,
      "skellam_draw": 0.243,
      "skellam_loss": 0.3785
    },
    {
      "home": "WINNER M99",
      "away": "WINNER M100",
      "lambda_home": 1.5,
      "lambda_away": 1.5,
      "skellam_win": 0.3785,
      "skellam_draw": 0.243,
      "skellam_loss": 0.3785
    },
    {
      "home": "LOSER M101",
      "away": "LOSER M102",
      "lambda_home": 1.5,
      "lambda_away": 1.5,
      "skellam_win": 0.3785,
      "skellam_draw": 0.243,
      "skellam_loss": 0.3785
    },
    {
      "home": "WINNER M101",
      "away": "WINNER M102",
      "lambda_home": 1.5,
      "lambda_away": 1.5,
      "skellam_win": 0.3785,
      "skellam_draw": 0.243,
      "skellam_loss": 0.3785
    }
  ],
  "knockout_bracket": {
    "round_of_32": [
      {
        "match": 73,
        "likely_winner": "South Korea",
        "predicted_score": "South Korea 2-0 Canada (16.92%)",
        "teams": [
          {
            "name": "Canada",
            "reach_pct": 29.38,
            "win_if_reached_pct": 44.76,
            "overall_win_pct": 13.15
          },
          {
            "name": "South Korea",
            "reach_pct": 29.12,
            "win_if_reached_pct": 58.1,
            "overall_win_pct": 16.92
          }
        ],
        "label": "2nd-A vs 2nd-B",
        "city": "Los Angeles"
      },
      {
        "match": 74,
        "likely_winner": "Germany",
        "predicted_score": "Germany 2-0 Czechia (48.93%)",
        "teams": [
          {
            "name": "Germany",
            "reach_pct": 68.18,
            "win_if_reached_pct": 71.77,
            "overall_win_pct": 48.93
          },
          {
            "name": "Czechia",
            "reach_pct": 20.21,
            "win_if_reached_pct": 38.79,
            "overall_win_pct": 7.84
          }
        ],
        "label": "1st-E vs 3rd (A/B/C/D/F)",
        "city": "Boston"
      },
      {
        "match": 75,
        "likely_winner": "Netherlands",
        "predicted_score": "Netherlands 1-0 Morocco (44.38%)",
        "teams": [
          {
            "name": "Netherlands",
            "reach_pct": 66.63,
            "win_if_reached_pct": 66.61,
            "overall_win_pct": 44.38
          },
          {
            "name": "Morocco",
            "reach_pct": 37.36,
            "win_if_reached_pct": 40.31,
            "overall_win_pct": 15.06
          }
        ],
        "label": "1st-F vs 2nd-C",
        "city": "Monterrey"
      },
      {
        "match": 76,
        "likely_winner": "Brazil",
        "predicted_score": "Brazil 1-4 Sweden (33.57%)",
        "teams": [
          {
            "name": "Brazil",
            "reach_pct": 53.18,
            "win_if_reached_pct": 63.13,
            "overall_win_pct": 33.57
          },
          {
            "name": "Sweden",
            "reach_pct": 33.43,
            "win_if_reached_pct": 40.92,
            "overall_win_pct": 13.68
          }
        ],
        "label": "1st-C vs 2nd-F",
        "city": "Houston"
      },
      {
        "match": 77,
        "likely_winner": "France",
        "predicted_score": "France 3-0 Scotland (41.96%)",
        "teams": [
          {
            "name": "France",
            "reach_pct": 59.55,
            "win_if_reached_pct": 70.46,
            "overall_win_pct": 41.96
          },
          {
            "name": "Scotland",
            "reach_pct": 21.77,
            "win_if_reached_pct": 30.68,
            "overall_win_pct": 6.68
          }
        ],
        "label": "1st-I vs 3rd (C/D/F/G/H)",
        "city": "New York/New Jersey"
      },
      {
        "match": 78,
        "likely_winner": "Senegal",
        "predicted_score": "Senegal 2-1 Norway (20.68%)",
        "teams": [
          {
            "name": "Senegal",
            "reach_pct": 32.0,
            "win_if_reached_pct": 64.62,
            "overall_win_pct": 20.68
          },
          {
            "name": "Norway",
            "reach_pct": 31.66,
            "win_if_reached_pct": 64.12,
            "overall_win_pct": 20.3
          }
        ],
        "label": "2nd-E vs 2nd-I",
        "city": "Dallas"
      },
      {
        "match": 79,
        "likely_winner": "Mexico",
        "predicted_score": "Mexico 1-2 Ivory Coast (34.9%)",
        "teams": [
          {
            "name": "Mexico",
            "reach_pct": 50.9,
            "win_if_reached_pct": 68.57,
            "overall_win_pct": 34.9
          },
          {
            "name": "Ivory Coast",
            "reach_pct": 20.46,
            "win_if_reached_pct": 34.36,
            "overall_win_pct": 7.03
          }
        ],
        "label": "1st-A vs 3rd (C/E/F/H/I)",
        "city": "Mexico City"
      },
      {
        "match": 80,
        "likely_winner": "England",
        "predicted_score": "England 3-1 Croatia (30.46%)",
        "teams": [
          {
            "name": "England",
            "reach_pct": 45.76,
            "win_if_reached_pct": 66.56,
            "overall_win_pct": 30.46
          },
          {
            "name": "Croatia",
            "reach_pct": 40.05,
            "win_if_reached_pct": 66.72,
            "overall_win_pct": 26.72
          }
        ],
        "label": "1st-L vs 3rd (E/H/I/J/K)",
        "city": "Atlanta"
      },
      {
        "match": 81,
        "likely_winner": "USA",
        "predicted_score": "USA 2-1 T\u00fcrkiye (28.12%)",
        "teams": [
          {
            "name": "USA",
            "reach_pct": 42.32,
            "win_if_reached_pct": 66.45,
            "overall_win_pct": 28.12
          },
          {
            "name": "T\u00fcrkiye",
            "reach_pct": 25.67,
            "win_if_reached_pct": 57.77,
            "overall_win_pct": 14.83
          }
        ],
        "label": "1st-D vs 3rd (B/E/F/I/J)",
        "city": "San Francisco"
      },
      {
        "match": 82,
        "likely_winner": "Belgium",
        "predicted_score": "Belgium 2-0 Egypt (34.31%)",
        "teams": [
          {
            "name": "Belgium",
            "reach_pct": 57.0,
            "win_if_reached_pct": 60.19,
            "overall_win_pct": 34.31
          },
          {
            "name": "Egypt",
            "reach_pct": 21.97,
            "win_if_reached_pct": 45.79,
            "overall_win_pct": 10.06
          }
        ],
        "label": "1st-G vs 3rd (A/E/H/I/J)",
        "city": "Seattle"
      },
      {
        "match": 83,
        "likely_winner": "Colombia",
        "predicted_score": "Colombia 3-0 Congo DR (20.26%)",
        "teams": [
          {
            "name": "Colombia",
            "reach_pct": 38.93,
            "win_if_reached_pct": 52.04,
            "overall_win_pct": 20.26
          },
          {
            "name": "Congo DR",
            "reach_pct": 16.57,
            "win_if_reached_pct": 34.22,
            "overall_win_pct": 5.67
          }
        ],
        "label": "2nd-K vs 2nd-L",
        "city": "Toronto"
      },
      {
        "match": 84,
        "likely_winner": "Spain",
        "predicted_score": "Spain 5-2 Austria (50.92%)",
        "teams": [
          {
            "name": "Spain",
            "reach_pct": 68.99,
            "win_if_reached_pct": 73.81,
            "overall_win_pct": 50.92
          },
          {
            "name": "Austria",
            "reach_pct": 39.85,
            "win_if_reached_pct": 34.28,
            "overall_win_pct": 13.66
          }
        ],
        "label": "1st-H vs 2nd-J",
        "city": "Los Angeles"
      },
      {
        "match": 85,
        "likely_winner": "Switzerland",
        "predicted_score": "Switzerland 4-1 Bosnia-Herzegovina (29.25%)",
        "teams": [
          {
            "name": "Switzerland",
            "reach_pct": 48.55,
            "win_if_reached_pct": 60.25,
            "overall_win_pct": 29.25
          },
          {
            "name": "Bosnia-Herzegovina",
            "reach_pct": 16.13,
            "win_if_reached_pct": 47.68,
            "overall_win_pct": 7.69
          }
        ],
        "label": "1st-B vs 3rd (E/F/G/I/J)",
        "city": "Vancouver"
      },
      {
        "match": 86,
        "likely_winner": "Argentina",
        "predicted_score": "Argentina 2-1 Uruguay (48.11%)",
        "teams": [
          {
            "name": "Argentina",
            "reach_pct": 70.06,
            "win_if_reached_pct": 68.67,
            "overall_win_pct": 48.11
          },
          {
            "name": "Uruguay",
            "reach_pct": 42.21,
            "win_if_reached_pct": 40.11,
            "overall_win_pct": 16.93
          }
        ],
        "label": "1st-J vs 2nd-H",
        "city": "Miami"
      },
      {
        "match": 87,
        "likely_winner": "Portugal",
        "predicted_score": "Portugal 1-0 Panama (38.85%)",
        "teams": [
          {
            "name": "Portugal",
            "reach_pct": 56.78,
            "win_if_reached_pct": 68.42,
            "overall_win_pct": 38.85
          },
          {
            "name": "Panama",
            "reach_pct": 20.96,
            "win_if_reached_pct": 30.3,
            "overall_win_pct": 6.35
          }
        ],
        "score_90": "0-0",
        "score_120": "1-0",
        "went_to_et": true,
        "went_to_penalties": false,
        "et_lambda_home": 0.7221,
        "et_lambda_away": 0.2443,
        "label": "1st-K vs 3rd (D/E/I/J/L)",
        "city": "Kansas City"
      },
      {
        "match": 88,
        "likely_winner": "Australia",
        "predicted_score": "Australia 2-2 Iran (14.3%)",
        "teams": [
          {
            "name": "Iran",
            "reach_pct": 30.95,
            "win_if_reached_pct": 45.69,
            "overall_win_pct": 14.14
          },
          {
            "name": "Australia",
            "reach_pct": 26.34,
            "win_if_reached_pct": 54.29,
            "overall_win_pct": 14.3
          }
        ],
        "score_90": "2-2",
        "score_120": "2-2",
        "went_to_et": true,
        "went_to_penalties": true,
        "et_lambda_home": 0.424,
        "et_lambda_away": 0.416,
        "label": "2nd-D vs 2nd-G",
        "city": "Dallas"
      }
    ],
    "round_of_16": [
      {
        "match": 89,
        "likely_winner": "Germany",
        "predicted_score": "Germany 2-3 France (26.27%)",
        "teams": [
          {
            "name": "Germany",
            "reach_pct": 48.93,
            "win_if_reached_pct": 53.69,
            "overall_win_pct": 26.27
          },
          {
            "name": "France",
            "reach_pct": 41.96,
            "win_if_reached_pct": 57.17,
            "overall_win_pct": 23.99
          }
        ]
      },
      {
        "match": 90,
        "likely_winner": "Netherlands",
        "predicted_score": "Netherlands 4-1 South Korea (32.4%)",
        "teams": [
          {
            "name": "Netherlands",
            "reach_pct": 44.38,
            "win_if_reached_pct": 73.01,
            "overall_win_pct": 32.4
          },
          {
            "name": "South Korea",
            "reach_pct": 16.92,
            "win_if_reached_pct": 30.79,
            "overall_win_pct": 5.21
          }
        ]
      },
      {
        "match": 91,
        "likely_winner": "Brazil",
        "predicted_score": "Brazil 2-2 Senegal (21.7%)",
        "teams": [
          {
            "name": "Brazil",
            "reach_pct": 33.57,
            "win_if_reached_pct": 64.64,
            "overall_win_pct": 21.7
          },
          {
            "name": "Senegal",
            "reach_pct": 20.68,
            "win_if_reached_pct": 41.59,
            "overall_win_pct": 8.6
          }
        ],
        "score_90": "2-2",
        "score_120": "2-2",
        "went_to_et": true,
        "went_to_penalties": true,
        "et_lambda_home": 0.6122,
        "et_lambda_away": 0.2881
      },
      {
        "match": 92,
        "likely_winner": "England",
        "predicted_score": "England 0-0 Mexico (18.19%)",
        "teams": [
          {
            "name": "Mexico",
            "reach_pct": 34.9,
            "win_if_reached_pct": 52.03,
            "overall_win_pct": 18.16
          },
          {
            "name": "England",
            "reach_pct": 30.46,
            "win_if_reached_pct": 59.72,
            "overall_win_pct": 18.19
          }
        ],
        "score_90": "0-0",
        "score_120": "0-0",
        "went_to_et": true,
        "went_to_penalties": true,
        "et_lambda_home": 0.5467,
        "et_lambda_away": 0.3226
      },
      {
        "match": 93,
        "likely_winner": "Spain",
        "predicted_score": "Spain 2-1 Croatia (35.22%)",
        "teams": [
          {
            "name": "Spain",
            "reach_pct": 50.92,
            "win_if_reached_pct": 69.17,
            "overall_win_pct": 35.22
          },
          {
            "name": "Croatia",
            "reach_pct": 20.45,
            "win_if_reached_pct": 40.98,
            "overall_win_pct": 8.38
          }
        ]
      },
      {
        "match": 94,
        "likely_winner": "Belgium",
        "predicted_score": "Belgium 3-2 USA (18.71%)",
        "teams": [
          {
            "name": "Belgium",
            "reach_pct": 34.31,
            "win_if_reached_pct": 54.53,
            "overall_win_pct": 18.71
          },
          {
            "name": "USA",
            "reach_pct": 31.1,
            "win_if_reached_pct": 58.75,
            "overall_win_pct": 18.27
          }
        ]
      },
      {
        "match": 95,
        "likely_winner": "Argentina",
        "predicted_score": "Argentina 0-1 Uruguay (34.7%)",
        "teams": [
          {
            "name": "Argentina",
            "reach_pct": 48.11,
            "win_if_reached_pct": 72.13,
            "overall_win_pct": 34.7
          },
          {
            "name": "Uruguay",
            "reach_pct": 16.93,
            "win_if_reached_pct": 70.41,
            "overall_win_pct": 11.92
          }
        ]
      },
      {
        "match": 96,
        "likely_winner": "Portugal",
        "predicted_score": "Portugal 2-1 Colombia (26.57%)",
        "teams": [
          {
            "name": "Portugal",
            "reach_pct": 42.01,
            "win_if_reached_pct": 63.25,
            "overall_win_pct": 26.57
          },
          {
            "name": "Colombia",
            "reach_pct": 29.72,
            "win_if_reached_pct": 61.37,
            "overall_win_pct": 18.24
          }
        ]
      }
    ],
    "quarter_finals": [
      {
        "match": 97,
        "likely_winner": "Netherlands",
        "predicted_score": "Netherlands 2-3 Germany (17.11%)",
        "teams": [
          {
            "name": "Netherlands",
            "reach_pct": 32.66,
            "win_if_reached_pct": 52.39,
            "overall_win_pct": 17.11
          },
          {
            "name": "Germany",
            "reach_pct": 26.27,
            "win_if_reached_pct": 57.94,
            "overall_win_pct": 15.22
          }
        ]
      },
      {
        "match": 98,
        "likely_winner": "Spain",
        "predicted_score": "Spain 3-1 Belgium (25.03%)",
        "teams": [
          {
            "name": "Spain",
            "reach_pct": 35.22,
            "win_if_reached_pct": 71.07,
            "overall_win_pct": 25.03
          },
          {
            "name": "Belgium",
            "reach_pct": 18.71,
            "win_if_reached_pct": 37.09,
            "overall_win_pct": 6.94
          }
        ]
      },
      {
        "match": 99,
        "likely_winner": "Brazil",
        "predicted_score": "Brazil 0-2 England (12.14%)",
        "teams": [
          {
            "name": "Brazil",
            "reach_pct": 21.7,
            "win_if_reached_pct": 55.94,
            "overall_win_pct": 12.14
          },
          {
            "name": "England",
            "reach_pct": 18.19,
            "win_if_reached_pct": 48.93,
            "overall_win_pct": 8.9
          }
        ]
      },
      {
        "match": 100,
        "likely_winner": "Argentina",
        "predicted_score": "Argentina 2-0 Portugal (21.97%)",
        "teams": [
          {
            "name": "Argentina",
            "reach_pct": 34.8,
            "win_if_reached_pct": 63.13,
            "overall_win_pct": 21.97
          },
          {
            "name": "Portugal",
            "reach_pct": 26.57,
            "win_if_reached_pct": 46.33,
            "overall_win_pct": 12.31
          }
        ]
      }
    ],
    "semi_finals": [
      {
        "match": 101,
        "likely_winner": "Spain",
        "predicted_score": "Spain 1-2 Netherlands (13.42%)",
        "teams": [
          {
            "name": "Spain",
            "reach_pct": 25.04,
            "win_if_reached_pct": 53.59,
            "overall_win_pct": 13.42
          },
          {
            "name": "Netherlands",
            "reach_pct": 17.4,
            "win_if_reached_pct": 57.59,
            "overall_win_pct": 10.02
          }
        ]
      },
      {
        "match": 102,
        "likely_winner": "Argentina",
        "predicted_score": "Argentina 2-0 Portugal (12.18%)",
        "teams": [
          {
            "name": "Argentina",
            "reach_pct": 22.09,
            "win_if_reached_pct": 55.14,
            "overall_win_pct": 12.18
          },
          {
            "name": "Portugal",
            "reach_pct": 12.35,
            "win_if_reached_pct": 50.36,
            "overall_win_pct": 6.22
          }
        ]
      }
    ],
    "third_place_match": {
      "match": 103,
      "likely_winner": "Spain",
      "predicted_score": "Spain 1-3 Argentina (8.02%)",
      "teams": [
        {
          "name": "Spain",
          "reach_pct": 14.02,
          "win_if_reached_pct": 57.2,
          "overall_win_pct": 8.02
        },
        {
          "name": "Argentina",
          "reach_pct": 11.69,
          "win_if_reached_pct": 50.38,
          "overall_win_pct": 5.89
        }
      ]
    },
    "third_place_match_derived": {
      "match": 103,
      "city": "Miami",
      "likely_winner": "Netherlands",
      "predicted_score": "Netherlands 4-2 Brazil (5.4%)",
      "teams": [
        {
          "name": "Netherlands",
          "reach_pct": 9.35,
          "win_if_reached_pct": 57.75,
          "overall_win_pct": 5.4
        },
        {
          "name": "Brazil",
          "reach_pct": 8.24,
          "win_if_reached_pct": 52.18,
          "overall_win_pct": 4.3
        }
      ]
    },
    "final": {
      "match": 104,
      "likely_winner": "Spain",
      "predicted_score": "Spain 1-1 Argentina (9.35%)",
      "teams": [
        {
          "name": "Spain",
          "reach_pct": 16.48,
          "win_if_reached_pct": 56.74,
          "overall_win_pct": 9.35
        },
        {
          "name": "Argentina",
          "reach_pct": 13.92,
          "win_if_reached_pct": 49.64,
          "overall_win_pct": 6.91
        }
      ],
      "score_90": "1-1",
      "score_120": "1-1",
      "went_to_et": true,
      "went_to_penalties": true,
      "et_lambda_home": 0.4391,
      "et_lambda_away": 0.4018
    }
  },
  "golden_boot_probabilities": [
    {
      "player": "Mikel Oyarzabal",
      "team": "Spain",
      "golden_boot_pct": 18.33,
      "mean_goals": 8.32,
      "expected_matches": 5.62,
      "is_penalty_taker": true,
      "is_proxy": false
    },
    {
      "player": "Lautaro Mart\u00ednez",
      "team": "Argentina",
      "golden_boot_pct": 9.79,
      "mean_goals": 6.86,
      "expected_matches": 5.46,
      "is_penalty_taker": false,
      "is_proxy": false
    },
    {
      "player": "Kylian Mbapp\u00e9",
      "team": "France",
      "golden_boot_pct": 7.2,
      "mean_goals": 6.5,
      "expected_matches": 5.22,
      "is_penalty_taker": true,
      "is_proxy": false
    },
    {
      "player": "Germany (squad avg)",
      "team": "Germany",
      "golden_boot_pct": 6.87,
      "mean_goals": 6.5,
      "expected_matches": 5.25,
      "is_penalty_taker": true,
      "is_proxy": true
    },
    {
      "player": "X. Simons",
      "team": "Netherlands",
      "golden_boot_pct": 5.18,
      "mean_goals": 6.08,
      "expected_matches": 5.35,
      "is_penalty_taker": true,
      "is_proxy": false
    },
    {
      "player": "Keito Nakamura",
      "team": "Japan",
      "golden_boot_pct": 4.85,
      "mean_goals": 5.13,
      "expected_matches": 4.0,
      "is_penalty_taker": true,
      "is_proxy": false
    },
    {
      "player": "Mexico (squad avg)",
      "team": "Mexico",
      "golden_boot_pct": 3.81,
      "mean_goals": 5.53,
      "expected_matches": 5.03,
      "is_penalty_taker": true,
      "is_proxy": true
    },
    {
      "player": "Colombia (squad avg)",
      "team": "Colombia",
      "golden_boot_pct": 3.25,
      "mean_goals": 5.27,
      "expected_matches": 4.89,
      "is_penalty_taker": true,
      "is_proxy": true
    },
    {
      "player": "USA (squad avg)",
      "team": "USA",
      "golden_boot_pct": 3.03,
      "mean_goals": 5.1,
      "expected_matches": 4.87,
      "is_penalty_taker": true,
      "is_proxy": true
    },
    {
      "player": "L. Trossard",
      "team": "Belgium",
      "golden_boot_pct": 2.96,
      "mean_goals": 5.43,
      "expected_matches": 4.84,
      "is_penalty_taker": true,
      "is_proxy": false
    },
    {
      "player": "A. Budimir",
      "team": "Croatia",
      "golden_boot_pct": 2.45,
      "mean_goals": 4.97,
      "expected_matches": 4.97,
      "is_penalty_taker": true,
      "is_proxy": false
    },
    {
      "player": "Youssef En-Nesyri",
      "team": "Morocco",
      "golden_boot_pct": 2.14,
      "mean_goals": 4.51,
      "expected_matches": 4.74,
      "is_penalty_taker": true,
      "is_proxy": false
    },
    {
      "player": "T. Reijnders",
      "team": "Netherlands",
      "golden_boot_pct": 2.1,
      "mean_goals": 4.9,
      "expected_matches": 5.35,
      "is_penalty_taker": false,
      "is_proxy": false
    },
    {
      "player": "Endrick",
      "team": "Brazil",
      "golden_boot_pct": 2.01,
      "mean_goals": 4.72,
      "expected_matches": 5.07,
      "is_penalty_taker": true,
      "is_proxy": false
    },
    {
      "player": "Austria (squad avg)",
      "team": "Austria",
      "golden_boot_pct": 1.94,
      "mean_goals": 4.25,
      "expected_matches": 4.46,
      "is_penalty_taker": true,
      "is_proxy": true
    },
    {
      "player": "J. Bellingham",
      "team": "England",
      "golden_boot_pct": 1.85,
      "mean_goals": 4.71,
      "expected_matches": 5.04,
      "is_penalty_taker": true,
      "is_proxy": false
    },
    {
      "player": "Switzerland (squad avg)",
      "team": "Switzerland",
      "golden_boot_pct": 1.7,
      "mean_goals": 4.85,
      "expected_matches": 4.63,
      "is_penalty_taker": true,
      "is_proxy": true
    },
    {
      "player": "Darwin Nunez",
      "team": "Uruguay",
      "golden_boot_pct": 1.62,
      "mean_goals": 4.2,
      "expected_matches": 4.63,
      "is_penalty_taker": true,
      "is_proxy": false
    },
    {
      "player": "Norway (squad avg)",
      "team": "Norway",
      "golden_boot_pct": 1.59,
      "mean_goals": 4.16,
      "expected_matches": 4.48,
      "is_penalty_taker": true,
      "is_proxy": true
    },
    {
      "player": "Sweden (squad avg)",
      "team": "Sweden",
      "golden_boot_pct": 1.5,
      "mean_goals": 3.93,
      "expected_matches": 4.33,
      "is_penalty_taker": true,
      "is_proxy": true
    }
  ]
}